jaraco/__init__.py
jaraco/apt.py
jaraco.apt-2.0.dist-info/LICENSE
jaraco.apt-2.0.dist-info/METADATA
jaraco.apt-2.0.dist-info/WHEEL
jaraco.apt-2.0.dist-info/top_level.txt
jaraco.apt-2.0.dist-info/RECORD
